LICENSE
MANIFEST.in
README.md
requirements.txt
setup.py
pagure_importer/__init__.py
pagure_importer/app.py
pagure_importer.egg-info/PKG-INFO
pagure_importer.egg-info/SOURCES.txt
pagure_importer.egg-info/dependency_links.txt
pagure_importer.egg-info/entry_points.txt
pagure_importer.egg-info/not-zip-safe
pagure_importer.egg-info/requires.txt
pagure_importer.egg-info/top_level.txt
pagure_importer/commands/__init__.py
pagure_importer/commands/clone.py
pagure_importer/commands/fedorahosted.py
pagure_importer/commands/github.py
pagure_importer/commands/mkconfig.py
pagure_importer/commands/push.py
pagure_importer/utils/__init__.py
pagure_importer/utils/exceptions.py
pagure_importer/utils/fas.py
pagure_importer/utils/git.py
pagure_importer/utils/importer_github.py
pagure_importer/utils/importer_trac.py
pagure_importer/utils/models.py