Metadata-Version: 1.1
Name: pagure-importer
Version: 2.2.2
Summary: CLI tool for imports to Pagure
Home-page: https://pagure.io/pagure-importer
Author: Vivek Anand
Author-email: vivekanand1101@gmail.com
License: GNU General Public License v2.0
Keywords: pagure,importer,import
Platform: UNKNOWN
Classifier: Intended Audience :: Developers
Classifier: Intended Audience :: Information Technology
Classifier: Programming Language :: Python
Classifier: Programming Language :: Python :: 3 :: Only
